Workbook

Sheet Painel
B2: PAINEL — FAIXAS DE REFERÊNCIA POR FORMATO
B3: Sínteses calculadas a partir da aba Catalogo. Todos os valores são R$/mês por unidade.
B5: Faixa geral do catálogo (mín. – máx.)
B6: Locação SECA — mínimo | C6: =MIN(Catalogo!H5:H29) -> 16500
B7: Locação SECA — máximo | C7: =MAX(Catalogo!H5:H29) -> 174000
B8: TURNKEY — mínimo | C8: =MIN(Catalogo!L5:L29) -> 100989.83
B9: TURNKEY — máximo | C9: =MAX(Catalogo!L5:L29) -> 697057.63
B11: Média por plataforma
B12: Plataforma | C12: SECA média (R$/mês) | D12: TURNKEY média (R$/mês)
B13: Van | C13: =AVERAGEIF(Catalogo!$D$5:$D$29,"Van",Catalogo!H5:H29) -> 19066.667 | D13: =AVERAGEIF(Catalogo!$D$5:$D$29,"Van",Catalogo!L5:L29) -> 147915.93
B14: Caminhão | C14: =AVERAGEIF(Catalogo!$D$5:$D$29,"Caminhão",Catalogo!H5:H29) -> 38666.667 | D14: =AVERAGEIF(Catalogo!$D$5:$D$29,"Caminhão",Catalogo!L5:L29) -> 238427.12
B15: Carreta | C15: =AVERAGEIF(Catalogo!$D$5:$D$29,"Carreta",Catalogo!H5:H29) -> 94714.286 | D15: =AVERAGEIF(Catalogo!$D$5:$D$29,"Carreta",Catalogo!L5:L29) -> 526752.54
B18: Como usar este prospecto:
B19: 1) Ajuste as 5 premissas (aba Premissas) e os valores-base de veículo (aba Veiculos) ao seu cenário.
B20: 2) Para cada serviço, edite o Kit de equipamentos e o custo de Equipe+Insumos (colunas amarelas).
B21: 3) Leia SECA (locação do ativo) e TURNKEY (operação completa) já calculados, com versão Amazônia Legal.
B22: 4) Para consulta pública no portal brain27, a aba Catalogo pode ser exportada em CSV/JSON — posso gerar.
B23: 5) Estes números são referência de planejamento; confirme com 3 cotações de mercado antes de propor preço firme.

Sheet Catalogo
B2: PROSPECTO G3 — CATÁLOGO DE SERVIÇOS MÓVEIS · LOCAÇÃO SECA E TURNKEY
B3: Edite apenas as colunas amarelas (Kit de equipamentos e Equipe/Insumos). O restante é calculado. Valores = estimativas de referência p/ consulta de mercado.
B4: Categoria | C4: Serviço | D4: Plataforma | E4: Veículo base (R$) | F4: Kit equip. (R$) | G4: Ativo total (R$) | H4: Locação SECA (R$/mês) | I4: Operação (R$/mês) | J4: Equipe+Insumos (R$/mês) | K4: Custo direto (R$/mês) | L4: TURNKEY (R$/mês) | M4: TURNKEY Amaz. Legal (R$/mês) | N4: Atend./mês | O4: Observação
B5: Saúde | C5: Odontologia / Saúde Bucal (1 cadeira) | D5: Van | E5: =INDEX(Veiculos!$C$5:$C$8,MATCH($D5,Veiculos!$B$5:$B$8,0)) -> 450000 | F5: 120000 | G5: =E5+F5 -> 570000 | H5: =G5*Premissas!$C$4 -> 17100 | I5: =INDEX(Veiculos!$D$5:$D$8,MATCH($D5,Veiculos!$B$5:$B$8,0)) -> 25000 | J5: 45000 | K5: =H5+I5+J5 -> 87100 | L5: =K5*(1+Premissas!$C$5)/(1-Premissas!$C$6-Premissas!$C$7) -> 132273.9 | M5: =L5*(1+Premissas!$C$8) -> 171956.07 | N5: 600 | O5: 1 cadeira; até ~600 atend./mês (base Eco X/Master)
B6: Saúde | C6: Odontologia (2 cadeiras) | D6: Caminhão | E6: =INDEX(Veiculos!$C$5:$C$8,MATCH($D6,Veiculos!$B$5:$B$8,0)) -> 900000 | F6: 250000 | G6: =E6+F6 -> 1150000 | H6: =G6*Premissas!$C$4 -> 34500 | I6: =INDEX(Veiculos!$D$5:$D$8,MATCH($D6,Veiculos!$B$5:$B$8,0)) -> 35000 | J6: 75000 | K6: =H6+I6+J6 -> 144500 | L6: =K6*(1+Premissas!$C$5)/(1-Premissas!$C$6-Premissas!$C$7) -> 219444.07 | M6: =L6*(1+Premissas!$C$8) -> 285277.29 | N6: 1200 | O6: 2 consultórios odonto
B7: Saúde | C7: Oftalmologia (consultas + exames) | D7: Caminhão | E7: =INDEX(Veiculos!$C$5:$C$8,MATCH($D7,Veiculos!$B$5:$B$8,0)) -> 900000 | F7: 400000 | G7: =E7+F7 -> 1300000 | H7: =G7*Premissas!$C$4 -> 39000 | I7: =INDEX(Veiculos!$D$5:$D$8,MATCH($D7,Veiculos!$B$5:$B$8,0)) -> 35000 | J7: 90000 | K7: =H7+I7+J7 -> 164000 | L7: =K7*(1+Premissas!$C$5)/(1-Premissas!$C$6-Premissas!$C$7) -> 249057.63 | M7: =L7*(1+Premissas!$C$8) -> 323774.92 | N7: 1000 | O7: Autorefr., lâmpada de fenda, retinógrafo, OCT
B8: Saúde | C8: Oftalmologia + Cirurgia de Catarata | D8: Carreta | E8: =INDEX(Veiculos!$C$5:$C$8,MATCH($D8,Veiculos!$B$5:$B$8,0)) -> 1300000 | F8: 900000 | G8: =E8+F8 -> 2200000 | H8: =G8*Premissas!$C$4 -> 66000 | I8: =INDEX(Veiculos!$D$5:$D$8,MATCH($D8,Veiculos!$B$5:$B$8,0)) -> 55000 | J8: 220000 | K8: =H8+I8+J8 -> 341000 | L8: =K8*(1+Premissas!$C$5)/(1-Premissas!$C$6-Premissas!$C$7) -> 517857.63 | M8: =L8*(1+Premissas!$C$8) -> 673214.92 | N8: 300 | O8: Centro cirúrgico faco; ref. AgSUS Tip.3
B9: Saúde | C9: Saúde da Mulher (mamografia + US + gineco) | D9: Carreta | E9: =INDEX(Veiculos!$C$5:$C$8,MATCH($D9,Veiculos!$B$5:$B$8,0)) -> 1300000 | F9: 1100000 | G9: =E9+F9 -> 2400000 | H9: =G9*Premissas!$C$4 -> 72000 | I9: =INDEX(Veiculos!$D$5:$D$8,MATCH($D9,Veiculos!$B$5:$B$8,0)) -> 55000 | J9: 180000 | K9: =H9+I9+J9 -> 307000 | L9: =K9*(1+Premissas!$C$5)/(1-Premissas!$C$6-Premissas!$C$7) -> 466223.73 | M9: =L9*(1+Premissas!$C$8) -> 606090.85 | N9: 900 | O9: Ref. AgSUS Tip.2 (fixo R$ 439k)
B10: Saúde | C10: Saúde do Homem (urologia) | D10: Caminhão | E10: =INDEX(Veiculos!$C$5:$C$8,MATCH($D10,Veiculos!$B$5:$B$8,0)) -> 900000 | F10: 250000 | G10: =E10+F10 -> 1150000 | H10: =G10*Premissas!$C$4 -> 34500 | I10: =INDEX(Veiculos!$D$5:$D$8,MATCH($D10,Veiculos!$B$5:$B$8,0)) -> 35000 | J10: 70000 | K10: =H10+I10+J10 -> 139500 | L10: =K10*(1+Premissas!$C$5)/(1-Premissas!$C$6-Premissas!$C$7) -> 211850.85 | M10: =L10*(1+Premissas!$C$8) -> 275406.1 | N10: 800 | O10: US, fluxometria, PSA, consultório
B11: Saúde | C11: Exame de Imagem — Tomografia (TC) | D11: Carreta | E11: =INDEX(Veiculos!$C$5:$C$8,MATCH($D11,Veiculos!$B$5:$B$8,0)) -> 1300000 | F11: 3200000 | G11: =E11+F11 -> 4500000 | H11: =G11*Premissas!$C$4 -> 135000 | I11: =INDEX(Veiculos!$D$5:$D$8,MATCH($D11,Veiculos!$B$5:$B$8,0)) -> 55000 | J11: 200000 | K11: =H11+I11+J11 -> 390000 | L11: =K11*(1+Premissas!$C$5)/(1-Premissas!$C$6-Premissas!$C$7) -> 592271.19 | M11: =L11*(1+Premissas!$C$8) -> 769952.54 | N11: 1200 | O11: Ref. AgSUS Tip.1 (fixo R$ 512k)
B12: Saúde | C12: Exame de Imagem — Ressonância (RM) | D12: Carreta | E12: =INDEX(Veiculos!$C$5:$C$8,MATCH($D12,Veiculos!$B$5:$B$8,0)) -> 1300000 | F12: 4500000 | G12: =E12+F12 -> 5800000 | H12: =G12*Premissas!$C$4 -> 174000 | I12: =INDEX(Veiculos!$D$5:$D$8,MATCH($D12,Veiculos!$B$5:$B$8,0)) -> 55000 | J12: 230000 | K12: =H12+I12+J12 -> 459000 | L12: =K12*(1+Premissas!$C$5)/(1-Premissas!$C$6-Premissas!$C$7) -> 697057.63 | M12: =L12*(1+Premissas!$C$8) -> 906174.92 | N12: 900 | O12: RM móvel high-end — estimativa, validar
B13: Saúde | C13: Radiologia Geral / Raio-X | D13: Caminhão | E13: =INDEX(Veiculos!$C$5:$C$8,MATCH($D13,Veiculos!$B$5:$B$8,0)) -> 900000 | F13: 350000 | G13: =E13+F13 -> 1250000 | H13: =G13*Premissas!$C$4 -> 37500 | I13: =INDEX(Veiculos!$D$5:$D$8,MATCH($D13,Veiculos!$B$5:$B$8,0)) -> 35000 | J13: 70000 | K13: =H13+I13+J13 -> 142500 | L13: =K13*(1+Premissas!$C$5)/(1-Premissas!$C$6-Premissas!$C$7) -> 216406.78 | M13: =L13*(1+Premissas!$C$8) -> 281328.81 | N13: 1500 | O13: RX digital + laudos
B14: Saúde | C14: Ultrassonografia Geral | D14: Van | E14: =INDEX(Veiculos!$C$5:$C$8,MATCH($D14,Veiculos!$B$5:$B$8,0)) -> 450000 | F14: 300000 | G14: =E14+F14 -> 750000 | H14: =G14*Premissas!$C$4 -> 22500 | I14: =INDEX(Veiculos!$D$5:$D$8,MATCH($D14,Veiculos!$B$5:$B$8,0)) -> 25000 | J14: 80000 | K14: =H14+I14+J14 -> 127500 | L14: =K14*(1+Premissas!$C$5)/(1-Premissas!$C$6-Premissas!$C$7) -> 193627.12 | M14: =L14*(1+Premissas!$C$8) -> 251715.25 | N14: 1200 | O14: US multipropósito + laudos
B15: Saúde | C15: Análises Clínicas / Coleta Laboratorial | D15: Van | E15: =INDEX(Veiculos!$C$5:$C$8,MATCH($D15,Veiculos!$B$5:$B$8,0)) -> 450000 | F15: 180000 | G15: =E15+F15 -> 630000 | H15: =G15*Premissas!$C$4 -> 18900 | I15: =INDEX(Veiculos!$D$5:$D$8,MATCH($D15,Veiculos!$B$5:$B$8,0)) -> 25000 | J15: 55000 | K15: =H15+I15+J15 -> 98900 | L15: =K15*(1+Premissas!$C$5)/(1-Premissas!$C$6-Premissas!$C$7) -> 150193.9 | M15: =L15*(1+Premissas!$C$8) -> 195252.07 | N15: 2000 | O15: Coleta + cadeia fria; análise externa
B16: Saúde | C16: Medicina Ocupacional / Saúde do Trabalhador | D16: Caminhão | E16: =INDEX(Veiculos!$C$5:$C$8,MATCH($D16,Veiculos!$B$5:$B$8,0)) -> 900000 | F16: 500000 | G16: =E16+F16 -> 1400000 | H16: =G16*Premissas!$C$4 -> 42000 | I16: =INDEX(Veiculos!$D$5:$D$8,MATCH($D16,Veiculos!$B$5:$B$8,0)) -> 35000 | J16: 90000 | K16: =H16+I16+J16 -> 167000 | L16: =K16*(1+Premissas!$C$5)/(1-Premissas!$C$6-Premissas!$C$7) -> 253613.56 | M16: =L16*(1+Premissas!$C$8) -> 329697.63 | N16: 2000 | O16: Audiometria, espirometria, ECG, acuidade, RX
... B29: Cidadania/Serviços | C29: Biblioteca / Cultura Móvel | D29: Van | E29: =INDEX(Veiculos!$C$5:$C$8,MATCH($D29,Veiculos!$B$5:$B$8,0)) -> 450000 | F29: 100000 | G29: =E29+F29 -> 550000 | H29: =G29*Premissas!$C$4 -> 16500 | I29: =INDEX(Veiculos!$D$5:$D$8,MATCH($D29,Veiculos!$B$5:$B$8,0)) -> 25000 | J29: 25000 | K29: =H29+I29+J29 -> 66500 | L29: =K29*(1+Premissas!$C$5)/(1-Premissas!$C$6-Premissas!$C$7) -> 100989.83 | M29: =L29*(1+Premissas!$C$8) -> 131286.78 | N29: 1000 | O29: Acervo, leitura, oficinas
B31: Legenda: AZUL/amarelo = você edita (kit e equipe/insumos). VERDE = puxado da aba Veiculos. PRETO = calculado. 'SECA' = só o ativo (carreta/caminhão/van + equipamentos), sem operação. 'TURNKEY' = operação completa com equipe, insumos, tributos e margem.

Sheet Veiculos
B2: PLATAFORMAS DE VEÍCULO (base = veículo + adaptação + gerador + climatização)
B4: Plataforma (chave) | C4: Veículo base (R$) | D4: Operação mensal (R$) | E4: Observação
B5: Van | C5: 450000 | D5: 25000 | E5: Furgão adaptado (Master/Sprinter/Ducato). Serviços leves e coleta.
B6: Caminhão | C6: 900000 | D6: 35000 | E6: Baú/VUC/toco, alguns expansíveis. Imagem média, odonto duplo, ocupacional.
B7: Carreta | C7: 1300000 | D7: 55000 | E7: Semirreboque 15 m expansível. Imagem pesada, cirúrgico. Cavalo p/ translado à parte.
B8: Ônibus | C8: 1100000 | D8: 45000 | E8: Ônibus adaptado (variante). Odonto múltiplo, capacitação, hemóvel.
B10: 'Operação mensal' cobre motorista, translado (combustível/pedágio/diárias), manutenção do veículo, seguro e mão de obra de apoio (recepção/limpeza) — NÃO inclui equipe assistencial (essa vai por serviço na aba Catalogo).

Sheet Premissas
B2: PREMISSAS DE PRECIFICAÇÃO (edite as células amarelas)
B4: Taxa de locação mensal (% do valor do ativo) | C4: 0.03 | D4: Padrão leasing de equip. médico em contrato estável (2,5%–3,5%). Contrato curto/cancelável eleva.
B5: Overhead administrativo (% do custo direto) | C5: 0.12 | D5: Estrutura, gestão, seguros administrativos, rateio de sede.
B6: Tributos sobre o preço (%) | C6: 0.1425 | D6: Lucro Presumido serviços de saúde (ISS+PIS+COFINS+IR+CSLL aprox.). Confirmar enquadramento.
B7: Margem / lucro sobre o preço (%) | C7: 0.12 | D7: Margem líquida-alvo do operador. Ajuste conforme risco e prazo do contrato.
B8: Adicional Amazônia Legal (%) | C8: 0.3 | D8: Uplift de custo logístico/operacional em Amazônia Legal (ref. contratos AgSUS).
B10: Fórmula do turnkey por serviço: Turnkey = (Seca + Operação + Equipe/Insumos) × (1+Overhead) ÷ (1 − Tributos − Margem). Seca = Ativo × Taxa de locação. Ativo = Veículo base (aba Veiculos) + Kit de equipamentos (aba Catalogo).

Sheet Ancoras_Mercado
B2: ÂNCORAS DE MERCADO (referências públicas para calibrar o modelo)
B4: Referência | C4: Valor (R$/unidade/mês) | D4: Escopo | E4: Fonte / observação
B5: AgSUS Ed. 28/2025 — Tip.1 Imagem (Tomografia) | C5: 721498.82 | D5: Turnkey (fixo 512.466,50 + variável 209.032,32) | E5: Edital AgSUS 28/2025, item 5.3
B6: AgSUS Ed. 29/2025 — Tip.2 Saúde da Mulher | C6: 650068.38 | D6: Turnkey (fixo 439.204,38 + variável 210.864,00) | E6: Resumo dos Editais AgSUS
B7: AgSUS Ed. 30/2025 — Tip.3 Oftalmo/Catarata | C7: 1906541.6 | D7: Turnkey (só variável; média p/ unidade) | E7: Resumo dos Editais AgSUS
B8: AgSUS — parcela FIXA Tip.1 (contém locação) | C8: 512466.5 | D8: Fixo mensal (inclui aluguel da UMS) | E8: Edital 28/2025, item 5.2
B9: AgSUS — parcela FIXA Tip.2 (contém locação) | C9: 439204.38 | D9: Fixo mensal (inclui aluguel da UMS) | E9: Resumo dos Editais AgSUS
B10: SES-SC 'Carretas da Saúde da Mulher' (2025) | C10: 500000 | D10: Turnkey c/ equipe (mamografia+US) | E10: Gov. SC, out/2025 (~R$ 1 mi/mês p/ 2 unidades)
B11: Aparecida de Goiânia PE 067/2026 (UMS mutirão) | C11: 85037.2 | D11: Turnkey por mutirão (rateio mensal aprox.) | E11: Global R$ 1.020.446,40 ÷ 12; multi-especialidade
B13: Leitura: a tarifa turnkey da AgSUS é generosa (programa federal de urgência, com margem folgada). Um turnkey 'praticável' de mercado tende a ficar ABAIXO da tarifa federal — por isso o motor deste prospecto gera valores conservadores frente às âncoras, o que é adequado para consulta de mercado e negociação.

Sheet Notas & Fontes
C2: NOTAS, PREMISSAS E ROADMAP DE INTEGRAÇÃO
C4: NATUREZA DOS VALORES
C5: Todos os valores são ESTIMATIVAS de referência para planejamento e consulta de mercado — não são cotações firmes.
C6: Kit de equipamentos e Equipe+Insumos são as duas variáveis que mais mudam o resultado: ajuste por serviço.
C7: Itens sinalizados 'validar' (Ressonância, Hemodiálise) têm maior incerteza — priorize cotação real.
C9: MOTOR DE CÁLCULO
C10: Ativo = Veículo base (aba Veiculos) + Kit de equipamentos (aba Catalogo).
C11: Locação SECA = Ativo × Taxa de locação mensal (aba Premissas).
C12: Turnkey = (Seca + Operação + Equipe/Insumos) × (1+Overhead) ÷ (1 − Tributos − Margem).
C13: Turnkey Amazônia Legal = Turnkey × (1 + Adicional AL).
C15: FORMATOS DE VEÍCULO
C16: Van/Furgão: serviços leves, coleta, consultório único — menor custo, maior alcance urbano.
... C31: Elaborado por G3 Health Service · estimativas técnicas · sujeitas a validação por cotação de mercado (2025/2026).
